docs/uwsgi.py
sample/__init__.py
sample/response.py
whakerpy/__init__.py
whakerpy/messages.py
whakerpy/htmlmaker/__init__.py
whakerpy/htmlmaker/hconsts.py
whakerpy/htmlmaker/hexc.py
whakerpy/htmlmaker/treeelts.py
whakerpy/htmlmaker/treeerror.py
whakerpy/htmlmaker/treenode.py
whakerpy/htmlmaker/basenodes/__init__.py
whakerpy/htmlmaker/basenodes/baseelts.py
whakerpy/htmlmaker/basenodes/basenode.py
whakerpy/htmlmaker/emptynodes/__init__.py
whakerpy/htmlmaker/emptynodes/emptyelts.py
whakerpy/htmlmaker/emptynodes/emptynode.py
whakerpy/htmlmaker/htmnodes/__init__.py
whakerpy/htmlmaker/htmnodes/htmelts.py
whakerpy/htmlmaker/htmnodes/htmnode.py
whakerpy/httpd/__init__.py
whakerpy/httpd/handler.py
whakerpy/httpd/hresponse.py
whakerpy/httpd/hserver.py
whakerpy/httpd/hstatus.py
whakerpy/httpd/hutils.py
whakerpy/httpd/permissions.py
whakerpy/webapp/__init__.py
whakerpy/webapp/webconfig.py
whakerpy/webapp/weblocalserver.py
whakerpy/webapp/webresponse.py
whakerpy/webapp/webwsgi.py
whakerpy-1.5.dist-info/licenses/AUTHORS.md
whakerpy-1.5.dist-info/licenses/LICENSE.md
whakerpy-1.5.dist-info/METADATA
whakerpy-1.5.dist-info/WHEEL
whakerpy-1.5.dist-info/top_level.txt
whakerpy-1.5.dist-info/RECORD
