Metadata-Version: 2.4
Name: WhakerPy
Version: 1.5
Summary: Web HTML maker in Python - a light web application framework
Author-email: Brigitte Bigi <contact@sppas.org>
Project-URL: Homepage, https://sourceforge.net/projects/whakerpy/
Project-URL: Documentation, https://whakerpy.sourceforge.io
Project-URL: Pypi, https://pypi.org/project/whakerpy/
Project-URL: Repository, https://git.code.sf.net/p/whakerpy/code
Keywords: python,html,httpd,dynamic,web,app,ui
Classifier: Programming Language :: Python :: 3
Classifier: License :: OSI Approved :: GNU Affero General Public License v3 or later (AGPLv3+)
Classifier: Operating System :: OS Independent
Classifier: Topic :: Internet :: WWW/HTTP :: Dynamic Content
Classifier: Topic :: Internet :: WWW/HTTP :: HTTP Servers
Classifier: Topic :: Software Development
Classifier: Intended Audience :: Developers
Classifier: Development Status :: 5 - Production/Stable
Requires-Python: >=3.9
License-File: LICENSE.md
License-File: AUTHORS.md
Provides-Extra: docs
Requires-Dist: pygments; extra == "docs"
Requires-Dist: markdown2; extra == "docs"
Requires-Dist: ClammingPy>=1.9; extra == "docs"
Provides-Extra: tests
Requires-Dist: coverage~=7.3.0; extra == "tests"
Requires-Dist: selenium~=4.18.1; extra == "tests"
Requires-Dist: python-dotenv~=1.0.0; extra == "tests"
Dynamic: license-file
